pypar/__init__.py
pypar/alignment.py
pypar/compare.py
pypar/phoneme.py
pypar/textgrid.py
pypar/word.py
pypar-0.0.5.dist-info/LICENSE
pypar-0.0.5.dist-info/METADATA
pypar-0.0.5.dist-info/WHEEL
pypar-0.0.5.dist-info/top_level.txt
pypar-0.0.5.dist-info/RECORD
