Metadata-Version: 2.1
Name: pypar
Version: 0.0.5
Summary: Python phoneme alignment representation
Home-page: https://github.com/maxrmorrison/pypar
Author: Max Morrison
Author-email: maxrmorrison@gmail.com
License: MIT
Keywords: align,duration,phoneme,speech
Classifier: License :: OSI Approved :: MIT License
License-File: LICENSE
Requires-Dist: numpy
